aide_sdk/__init__.py
aide_sdk/application.py
aide_sdk/inference/__init__.py
aide_sdk/inference/aideoperator.py
aide_sdk/inference/inference_manager.py
aide_sdk/logger/__init__.py
aide_sdk/logger/appender.py
aide_sdk/logger/logger.py
aide_sdk/manifests/__init__.py
aide_sdk/manifests/execution_context.py
aide_sdk/manifests/manifest.py
aide_sdk/messaging/__init__.py
aide_sdk/messaging/config.py
aide_sdk/messaging/elastic_api.py
aide_sdk/messaging/schemas/__init__.py
aide_sdk/messaging/schemas/event.py
aide_sdk/messaging/schemas/event_execution.py
aide_sdk/messaging/schemas/execution.py
aide_sdk/messaging/schemas/origin.py
aide_sdk/messaging/schemas/resource.py
aide_sdk/model/__init__.py
aide_sdk/model/dicom_image.py
aide_sdk/model/dicom_origin.py
aide_sdk/model/dicom_series.py
aide_sdk/model/event.py
aide_sdk/model/operatorcontext.py
aide_sdk/model/origin.py
aide_sdk/model/resource.py
aide_sdk/utils/__init__.py
aide_sdk/utils/dicom.py
aide_sdk/utils/exceptions.py
aide_sdk/utils/file_storage.py
aide_sdk/utils/helpers.py
aide_sdk-1.0.6.dist-info/LICENSE.md
aide_sdk-1.0.6.dist-info/WHEEL
aide_sdk-1.0.6.dist-info/METADATA
aide_sdk-1.0.6.dist-info/RECORD
