Metadata-Version: 2.1
Name: aide-sdk
Version: 1.0.6
Summary: AI Deployment Engine SDK. This package allows you to build AI inference models to be run on the AIDE platform.
Home-page: https://www.aicentre.co.uk/
License: Apache-2.0
Author: Answer Digital
Author-email: aicentre@answerdigital.com
Requires-Python: >=3.7,<4.0
Classifier: License :: OSI Approved :: Apache Software License
Classifier: Programming Language :: Python :: 3
Classifier: Programming Language :: Python :: 3.10
Classifier: Programming Language :: Python :: 3.7
Classifier: Programming Language :: Python :: 3.8
Classifier: Programming Language :: Python :: 3.9
Requires-Dist: aide-infra (==0.3.1.2)
Requires-Dist: dataclasses-json (>=0.5.4,<0.6.0)
Requires-Dist: elasticsearch (<=7.13.0)
Requires-Dist: elasticsearch-dsl (>=7.4.0,<8.0.0)
Requires-Dist: json-logging (>=1.3.0,<2.0.0)
Requires-Dist: jsonpickle (>=2.0.0,<3.0.0)
Requires-Dist: marshmallow (>=3.13.0,<4.0.0)
Requires-Dist: marshmallow-polyfield (>=5.10,<6.0)
Requires-Dist: pika (>=1.2.0,<2.0.0)
Requires-Dist: pydicom (==2.1.2)
Requires-Dist: pynetdicom (>=1.5.7,<2.0.0)
Requires-Dist: requests (>=2.26.0,<3.0.0)
Requires-Dist: simplejson (>=3.17.2,<4.0.0)
